{
  "code": 200,
  "data": {
    "description": "Radar meteo - vezi evoluția vremii interactiv și în timp real: ploi, furtuni, ninsori și nori, în România cât și în întreaga lume.",
    "external": {
      "alternate": {
        "https://es.weatherandradar.com/radar-meteorologico": {
          "hreflang": "es-US"
        },
        "https://www.climaeradar.com.br/radarclima": {
          "hreflang": "pt-BR"
        },
        "https://www.havadurumuveradar.com/hava-durumu-radari": {
          "hreflang": "tr-TR"
        },
        "https://www.idojarasesradar.hu/idojaras-terkep": {
          "hreflang": "hu-HU"
        },
        "https://www.kairosradar.gr/rantar-kairou": {
          "hreflang": "el-GR"
        },
        "https://www.meteoeradar.it/radar-meteo": {
          "hreflang": "it-IT"
        },
        "https://www.meteoetradar.be/carte-meteo": {
          "hreflang": "fr-BE"
        },
        "https://www.meteoetradar.ch/carte-meteo": {
          "hreflang": "fr-CH"
        },
        "https://www.meteoetradar.com/carte-meteo": {
          "hreflang": "fr-FR"
        },
        "https://www.meteoradar.ro/harta-meteo": {
          "hreflang": "ro-RO"
        },
        "https://www.meteounradars.lv/laikapstaklu-radars": {
          "hreflang": "lv-LV"
        },
        "https://www.orasonline.lt/oru-zemelapis": {
          "hreflang": "lt-LT"
        },
        "https://www.pocasiaradar.cz/meteoradar": {
          "hreflang": "cs-CZ"
        },
        "https://www.pocasieradar.sk/meteoradar": {
          "hreflang": "sk-SK"
        },
        "https://www.pogodairadar.com.ua/radar-pohody": {
          "hreflang": "uk-UA"
        },
        "https://www.pogodairadar.pl/radar-pogodowy": {
          "hreflang": "pl-PL"
        },
        "https://www.tempoeradar.pt/mapa-do-tempo": {
          "hreflang": "pt-PT"
        },
        "https://www.tiempoyradar.com.ar/radar-meteorologico": {
          "hreflang": "es-AR"
        },
        "https://www.tiempoyradar.es/radar-meteorologico": {
          "hreflang": "es-ES"
        },
        "https://www.vejrogradar.dk/vejrradar": {
          "hreflang": "da-DK"
        },
        "https://www.vremeiradar.bg/meteorologichen-radar": {
          "hreflang": "bg-BG"
        },
        "https://www.vremeradar.rs/vremenski-radar": {
          "hreflang": "sr-Latn-RS"
        },
        "https://www.vremeradar.si/vremenski-radar": {
          "hreflang": "sl-SI"
        },
        "https://www.vremetoiradar.com/vremenski-radar": {
          "hreflang": "mk-MK"
        },
        "https://www.vrijemeradar.ba/vremenski-radar": {
          "hreflang": "bs-BA"
        },
        "https://www.vrijemeradar.hr/vremenski-radar": {
          "hreflang": "hr-HR"
        },
        "https://www.vrijemeradar.me/vremenski-radar": {
          "hreflang": "sr-Latn-ME"
        },
        "https://www.weatherandradar.co.uk/weather-map": {
          "hreflang": "en-GB"
        },
        "https://www.weatherandradar.com/weather-map": {
          "hreflang": "en-US"
        },
        "https://www.weatherandradar.ie/weather-map": {
          "hreflang": "en-IE"
        },
        "https://www.weatherandradar.in/weather-map": {
          "hreflang": "en-IN"
        },
        "https://www.weerenradar.be/weerradar": {
          "hreflang": "nl-BE"
        },
        "https://www.weerenradar.nl/weerradar": {
          "hreflang": "nl-NL"
        }
      },
      "apple-touch-icon": {
        "https://www.meteoradar.ro/assets/icons/icon-192x192-safari.png": {
          "sizes": "192x192"
        }
      },
      "canonical": {
        "https://www.meteoradar.ro/harta-meteo": {}
      },
      "icon": {
        "https://www.meteoradar.ro/assets/icons/icon-192x192.png": {
          "sizes": "192x192"
        },
        "https://www.meteoradar.ro/favicon.ico": {
          "type": "image/x-icon"
        }
      },
      "manifest": {
        "https://www.meteoradar.ro/assets/manifest/ro-RO.webmanifest": {}
      },
      "preconnect": {
        "https://api-app.wetteronline.de/": {
          "crossorigin": ""
        },
        "https://api-web.wo-cloud.com/": {
          "crossorigin": ""
        },
        "https://images.ctfassets.net/": {},
        "https://purple-cdn.web-apps-prod.wo-cloud.com/": {},
        "https://radar.wo-cloud.com/": {
          "crossorigin": ""
        },
        "https://search.prod.geo.wo-cloud.com/": {
          "crossorigin": ""
        },
        "https://tiles.wo-cloud.com/": {
          "crossorigin": ""
        }
      },
      "preload": {
        "https://www.meteoradar.ro/assets/app-shell/ic_back.svg": {
          "_ngcontent-serverapp-c4010958647": "",
          "as": "image",
          "fetchpriority": "high"
        }
      }
    },
    "html": "<html lang=\"ro\" data-beasties-container=\"\" style=\"--wo-header-height: 85px;\" data-previous-scroll-y=\"-0px\" class=\"sp-message-open\"><head>\n    <meta charset=\"utf-8\">\n    <title>Radar meteo - Ploaie, furtuni, ninsori și nori în timp real </title>\n    <base href=\"/\">\n    <meta name=\"apple-mobile-web-app-status-bar-style\" content=\"black-translucent\">\n    \n      <meta name=\"viewport\" content=\"viewport-fit=contain\">\n    \n    \n\n    <link rel=\"icon\" sizes=\"192x192\" href=\"assets/icons/icon-192x192.png\">\n    <link rel=\"icon\" type=\"image/x-icon\" href=\"favicon.ico\">\n    <link rel=\"apple-touch-icon\" sizes=\"192x192\" href=\"assets/icons/icon-192x192-safari.png\">\n    <meta name=\"theme-color\" content=\"#10658e\">\n    <link rel=\"preconnect\" href=\"//api-app.wetteronline.de\" crossorigin=\"\">\n    <link rel=\"preconnect\" href=\"//search.prod.geo.wo-cloud.com\" crossorigin=\"\">\n    <link rel=\"preconnect\" href=\"//api-web.wo-cloud.com\" crossorigin=\"\">\n    <link rel=\"preconnect\" href=\"//tiles.wo-cloud.com\" crossorigin=\"\">\n    <link rel=\"preconnect\" href=\"//radar.wo-cloud.com\" crossorigin=\"\">\n    <link rel=\"preconnect\" href=\"https://images.ctfassets.net\">\n    <link rel=\"preconnect\" href=\"https://purple-cdn.web-apps-prod.wo-cloud.com\">\n\n    <script src=\"https://gdpr-tcfv2.sp-prod.net/wrapperMessagingWithoutDetection.js\"></script><script type=\"text/javascript\">\n      // SourcePoint CMP dialog script\n      // prettier-ignore\n      !function () { var e = function () { var e, t = \"__tcfapiLocator\", a = [], n = window; for (; n;) { try { if (n.frames[t]) { e = n; break } } catch (e) { } if (n === window.top) break; n = n.parent } e || (!function e() { var a = n.document, r = !!n.frames[t]; if (!r) if (a.body) { var i = a.createElement(\"iframe\"); i.style.cssText = \"display:none\", i.name = t, a.body.appendChild(i) } else setTimeout(e, 5); return !r }(), n.__tcfapi = function () { for (var e, t = arguments.length, n = new Array(t), r = 0; r < t; r++)n[r] = arguments[r]; if (!n.length) return a; if (\"setGdprApplies\" === n[0]) n.length > 3 && 2 === parseInt(n[1], 10) && \"boolean\" == typeof n[3] && (e = n[3], \"function\" == typeof n[2] && n[2](\"set\", !0)); else if (\"ping\" === n[0]) { var i = { gdprApplies: e, cmpLoaded: !1, cmpStatus: \"stub\" }; \"function\" == typeof n[2] && n[2](i) } else a.push(n) }, n.addEventListener(\"message\", (function (e) { var t = \"string\" == typeof e.data, a = {}; try { a = t ? JSON.parse(e.data) : e.data } catch (e) { } var n = a.__tcfapiCall; n && window.__tcfapi(n.command, n.version, (function (a, r) { var i = { __tcfapiReturn: { returnValue: a, success: r, callId: n.callId } }; t && (i = JSON.stringify(i)), e.source.postMessage(i, \"*\") }), n.parameter) }), !1)) }; \"undefined\" != typeof module ? module.exports = e : e() }();\n    </script>\n    \n      <script>\n        window.pwaDevice = 'pwa-desktop';\n      </script>\n    \n    \n    <script>\n      window.pwaVersion = '2026.7.1';\n      // Pre-Conditions\n      var versionNumberMatcher = /^\\d{4}\\.\\d{1,2}(\\.\\d{1,2})?$/gm;\n      var isProductionVersionNumber =\n        !!window.pwaVersion.match(versionNumberMatcher) || false;\n      if (isProductionVersionNumber) {\n        window.dataLayer = window.dataLayer || [];\n\n        window.gtag = function () {\n          dataLayer.push(arguments);\n        };\n        gtag('js', new Date());\n        gtag('consent', 'default', {\n          ad_user_data: 'denied',\n          ad_personalization: 'denied',\n          ad_storage: 'denied',\n          analytics_storage: 'denied',\n        });\n        window.pwaVersion != '2026.7.1' &&\n          gtag('set', 'user_properties', {\n            application: window.pwaDevice,\n          });\n      }\n    </script>\n  <style>html{font-family:sans-serif;-ms-text-size-adjust:100%;-webkit-text-size-adjust:100%}body{margin:0}*,*:before,*:after{box-sizing:border-box}html,body{height:100%;width:100%;-webkit-tap-highlight-color:transparent;scrollbar-width:auto;scrollbar-color:#10658e #e6eff3;touch-action:pan-x pan-y}@media print{html,body{-webkit-print-color-adjust:exact;print-color-adjust:exact}}body{margin:0;font-family:Roboto,-apple-system,BlinkMacSystemFont,Segoe UI,Helvetica,Arial,sans-serif,\"Apple Color Emoji\",\"Segoe UI Emoji\",Segoe UI Symbol;-webkit-font-smoothing:antialiased;color:#3c3c3c;--ad-horizontal-margin:12px;--wo-weather-header-content-width-desktop:970px;background:#fff}@media(hover:none){body{-webkit-user-select:none;user-select:none}}</style><style>html{font-family:sans-serif;-ms-text-size-adjust:100%;-webkit-text-size-adjust:100%}body{margin:0}a{background:transparent}a:focus{outline:thin dotted}a:active,a:hover{outline:0}img{border:0}*,*:before,*:after{box-sizing:border-box}a{color:inherit;text-decoration:none}html,body{height:100%;width:100%;-webkit-tap-highlight-color:transparent;scrollbar-width:auto;scrollbar-color:#10658e #e6eff3;touch-action:pan-x pan-y}@media print{html,body{-webkit-print-color-adjust:exact;print-color-adjust:exact}html .no-print,body .no-print{display:none!important}}body{margin:0;font-family:Roboto,-apple-system,BlinkMacSystemFont,Segoe UI,Helvetica,Arial,sans-serif,\"Apple Color Emoji\",\"Segoe UI Emoji\",Segoe UI Symbol;-webkit-font-smoothing:antialiased;color:#3c3c3c;--ad-horizontal-margin: 12px;--wo-weather-header-content-width-desktop: 970px;background:#fff}@media(hover:none){body{-webkit-user-select:none;user-select:none}}\n</style><link rel=\"stylesheet\" href=\"styles.18a6bd2bbf83e907.css\" media=\"all\" onload=\"this.media='all'\"><noscript><link rel=\"stylesheet\" href=\"styles.18a6bd2bbf83e907.css\" media=\"all\"></noscript><style>[_nghost-serverApp-c3453211982]{display:flex;justify-content:center;min-height:100%;flex-direction:column;--content-max-width: 970px;position:relative;width:970px;margin:0 auto;align-items:center}@media screen and (max-width:1602px){[_nghost-serverApp-c3453211982]{margin-left:max(8px,100vw - 1290px)}}.menu-open[_nghost-serverApp-c3453211982]   .app-content[_ngcontent-serverApp-c3453211982], .menu-open[_nghost-serverApp-c3453211982]   .footer-placeholder[_ngcontent-serverApp-c3453211982], .menu-open[_nghost-serverApp-c3453211982]   .footer-spacer[_ngcontent-serverApp-c3453211982]{filter:blur(2px);transition:filter .2s ease-out}[_nghost-serverApp-c3453211982]   .app-content[_ngcontent-serverApp-c3453211982], [_nghost-serverApp-c3453211982]   .footer-placeholder[_ngcontent-serverApp-c3453211982], [_nghost-serverApp-c3453211982]   .footer-spacer[_ngcontent-serverApp-c3453211982]{transition:filter .2s ease-out}.showing-radar[_nghost-serverApp-c3453211982]   wo-header[_ngcontent-serverApp-c3453211982]{margin-bottom:0}.showing-radar[_nghost-serverApp-c3453211982]   .app-content[_ngcontent-serverApp-c3453211982]{padding-bottom:0}.fullscreen-radar[_nghost-serverApp-c3453211982]{width:100%;margin:0}.fullscreen-radar[_nghost-serverApp-c3453211982]   .app-content[_ngcontent-serverApp-c3453211982]{min-width:100%;margin-top:0}.fullscreen-radar[_nghost-serverApp-c3453211982]   wo-header[_ngcontent-serverApp-c3453211982]{display:none}.no-header[_nghost-serverApp-c3453211982]   .app-content[_ngcontent-serverApp-c3453211982]{margin-top:0}.no-header[_nghost-serverApp-c3453211982]   wo-header[_ngcontent-serverApp-c3453211982]{display:none}.minimal-header[_nghost-serverApp-c3453211982]   .app-content[_ngcontent-serverApp-c3453211982]{margin-top:0}.app-content[_ngcontent-serverApp-c3453211982]{flex:1;margin-top:calc(93px + env(safe-area-inset-top))}.app-content.fullscreen-content[_ngcontent-serverApp-c3453211982]{margin-top:calc(85px + env(safe-area-inset-top))}.app-content[_ngcontent-serverApp-c3453211982]{padding-bottom:32px}.app-content[_ngcontent-serverApp-c3453211982]   .container[_ngcontent-serverApp-c3453211982]{width:970px;margin:0 auto}.app-content[_ngcontent-serverApp-c3453211982]{position:relative}.app-content.no-footer-distance[_ngcontent-serverApp-c3453211982]{padding-bottom:0}.app-content.fullscreen-content[_ngcontent-serverApp-c3453211982]{flex:1}</style><style>[_nghost-serverApp-c3262266537]{display:flex;position:fixed;z-index:100;width:970px;top:0;margin:0 auto;justify-content:center;background:#fff}.large[_nghost-serverApp-c3262266537]{height:calc(85px + env(safe-area-inset-top))}[_nghost-serverApp-c3262266537]:before{content:\"\";position:absolute;top:0;left:-10px;right:-10px;height:100%;background:#fff;pointer-events:none}[_nghost-serverApp-c3262266537]{-webkit-user-select:none;user-select:none}.minimal[_nghost-serverApp-c3262266537]:not(.is-scrolled)   .background[_ngcontent-serverApp-c3262266537]{opacity:0}.minimal[_nghost-serverApp-c3262266537]:not(.is-scrolled)   wo-progress[_ngcontent-serverApp-c3262266537]{display:none}.minimal[_nghost-serverApp-c3262266537]   .logo[_ngcontent-serverApp-c3262266537]{display:flex;align-items:center;height:40px;background:#10658ed9;border-radius:10px;padding:0 4px;transition:background-color .3s}.minimal[_nghost-serverApp-c3262266537]   .logo[_ngcontent-serverApp-c3262266537]   .header-title[_ngcontent-serverApp-c3262266537]{padding:.5px 0 2px}.minimal.is-scrolled[_nghost-serverApp-c3262266537]   .logo[_ngcontent-serverApp-c3262266537]{background:none}.header-bar[_ngcontent-serverApp-c3262266537]{display:flex;flex:1;z-index:1;border-radius:40px 0 0;position:relative;max-width:970px;justify-content:left;height:100%;padding:env(safe-area-inset-top) 0 0 20px;background:#10658e;background-image:url(assets/app-shell/isobaren_header_transparent.svg);background-size:572px 138px;border-bottom:1px solid #ffbe00;align-items:center}.header-bar[_ngcontent-serverApp-c3262266537]   .middle-item[_ngcontent-serverApp-c3262266537]{height:100%}.header-bar[_ngcontent-serverApp-c3262266537]   .middle-item[_ngcontent-serverApp-c3262266537] > *[_ngcontent-serverApp-c3262266537], .header-bar[_ngcontent-serverApp-c3262266537]   .middle-item[_ngcontent-serverApp-c3262266537]   .title[_ngcontent-serverApp-c3262266537]{position:absolute;display:flex;align-items:center;height:100%;margin-left:20px;transition:opacity .3s,background-color .3s;opacity:1;pointer-events:auto}.header-bar[_ngcontent-serverApp-c3262266537]   .middle-item[_ngcontent-serverApp-c3262266537] > *.hidden[_ngcontent-serverApp-c3262266537], .header-bar[_ngcontent-serverApp-c3262266537]   .middle-item[_ngcontent-serverApp-c3262266537]   .title.hidden[_ngcontent-serverApp-c3262266537]{opacity:0;pointer-events:none}.header-bar[_ngcontent-serverApp-c3262266537]   .middle-item[_ngcontent-serverApp-c3262266537]   a.logo[_ngcontent-serverApp-c3262266537]{outline:0;cursor:pointer;display:flex;height:calc(100% - env(safe-area-inset-top))}.header-bar[_ngcontent-serverApp-c3262266537]   .middle-item[_ngcontent-serverApp-c3262266537]   a.logo[_ngcontent-serverApp-c3262266537]   .header-title[_ngcontent-serverApp-c3262266537]{display:flex;justify-content:center;margin:0;width:260px;height:100%}.header-bar[_ngcontent-serverApp-c3262266537]   .middle-item[_ngcontent-serverApp-c3262266537]   a.logo[_ngcontent-serverApp-c3262266537]   img[_ngcontent-serverApp-c3262266537]{width:260px;height:100%}.header-bar[_ngcontent-serverApp-c3262266537]   .middle-item[_ngcontent-serverApp-c3262266537]   .title[_ngcontent-serverApp-c3262266537]{text-overflow:ellipsis;overflow:hidden;white-space:nowrap;color:#fff;font-size:22px;font-weight:400;cursor:pointer;max-width:85%}wo-progress[_ngcontent-serverApp-c3262266537]{position:absolute;top:100%;left:0;width:100%}wo-share-button[_ngcontent-serverApp-c3262266537]{--size: 28px}</style><style>[_nghost-serverApp-c1466088905]{position:relative;width:56px;height:56px;display:flex;justify-content:center;align-items:center}.button-container[_ngcontent-serverApp-c1466088905]{position:absolute;top:0;bottom:0}</style><style>.button-container[_ngcontent-serverApp-c1466088905]{left:0}img[_ngcontent-serverApp-c1466088905]{cursor:pointer}.close[_ngcontent-serverApp-c1466088905]{position:absolute;right:8px;top:50%;transform:translateY(-50%);cursor:pointer}wo-back-button[_ngcontent-serverApp-c1466088905]{height:100%}</style><style>[_nghost-serverApp-c4007100336]{transition:opacity .25s}.progress-line[_ngcontent-serverApp-c4007100336], .progress-line[_ngcontent-serverApp-c4007100336]:before{height:3px;width:100%}.progress-line[_ngcontent-serverApp-c4007100336]{position:relative;background-color:#fafafa;display:flex;box-shadow:0 2px 5px gray}.progress-line[_ngcontent-serverApp-c4007100336]:before{content:\"\";position:absolute;left:0;top:0;background-color:#ffbe00;animation:_ngcontent-serverApp-c4007100336_running-progress 2s cubic-bezier(.4,0,.2,1) infinite;transform-origin:left}@keyframes _ngcontent-serverApp-c4007100336_running-progress{0%{transform:translate(0) scaleX(0)}50%{transform:translate(25%) scaleX(.75)}to{transform:translate(100%) scaleX(0)}}</style><style>[_nghost-serverApp-c4137958609]{--icon-margin: 80px;pointer-events:none}.opened.first-render[_nghost-serverApp-c4137958609]{pointer-events:auto}.opened.first-render[_nghost-serverApp-c4137958609]   .backdrop[_ngcontent-serverApp-c4137958609]{opacity:1}.opened.first-render[_nghost-serverApp-c4137958609]   .menu[_ngcontent-serverApp-c4137958609]{display:flex}[_nghost-serverApp-c4137958609]{position:absolute;display:flex;inset:100% auto auto 0;height:calc(100vh - 85px)}@supports (height: 100dvh){[_nghost-serverApp-c4137958609]{height:calc(100dvh - 85px)}}.backdrop[_ngcontent-serverApp-c4137958609]{cursor:pointer;height:100vh;position:fixed;inset:0;z-index:200;opacity:0;transition:opacity .3s}.menu[_ngcontent-serverApp-c4137958609]{border-top:2px solid #ffbe00;width:344px;background:#10658e url(assets/app-shell/isobaren_menu.svg) 50% 0 no-repeat;display:none;bottom:0;z-index:201;background-size:cover;color:#fff;flex-direction:column;box-shadow:5px 0 6px #3c3c3c9c;transition:transform .3s}.scroll-blocking-svc-scrollable-item[_ngcontent-serverApp-c4137958609]{flex-grow:1;overflow:auto;touch-action:pan-x pan-y}.scroll-blocking-svc-scrollable-item[_ngcontent-serverApp-c4137958609]::-webkit-scrollbar-track{background:#ffffff40}.scroll-blocking-svc-scrollable-item[_ngcontent-serverApp-c4137958609]::-webkit-scrollbar-thumb{background-color:#00537f}hr[_ngcontent-serverApp-c4137958609]{border:0;border-top:1px solid rgba(255,255,255,.2)}.placemark[_ngcontent-serverApp-c4137958609]{overflow:hidden;text-overflow:ellipsis}</style><style>[_nghost-serverApp-c3402772825]{width:970px}.fullscreen-radar[_nghost-serverApp-c3402772825]{width:100%}wo-radar[_ngcontent-serverApp-c3402772825]{position:absolute;inset:0}wo-radar.immersive[_ngcontent-serverApp-c3402772825]{position:absolute;inset:0}</style><style>.container[_ngcontent-serverApp-c839895721]{top:0;height:100%;position:absolute}.container.left[_ngcontent-serverApp-c839895721]{right:calc(100% + 8px)}.container.right[_ngcontent-serverApp-c839895721]{left:calc(100% + 8px)}wo-ad[_ngcontent-serverApp-c839895721]{position:sticky;top:117px}</style><meta name=\"description\" content=\"Radar meteo - vezi evoluția vremii interactiv și în timp real: ploi, furtuni, ninsori și nori, în România cât și în întreaga lume.\"><meta name=\"robots\" content=\"index,follow\"><meta property=\"og:description\" content=\"Radar meteo - vezi evoluția vremii interactiv și în timp real: ploi, furtuni, ninsori și nori, în România cât și în întreaga lume.\"><meta property=\"og:url\" content=\"https://www.meteoradar.ro/harta-meteo\"><meta property=\"og:locale\" content=\"ro_RO\"><meta property=\"og:image\" content=\"https://www.meteoradar.ro/assets/logos/preview-teaser/ro-RO_logo-isobars_16x9.png\"><link hreflang=\"bg-BG\" rel=\"alternate\" href=\"https://www.vremeiradar.bg/meteorologichen-radar\"><link hreflang=\"bs-BA\" rel=\"alternate\" href=\"https://www.vrijemeradar.ba/vremenski-radar\"><link hreflang=\"cs-CZ\" rel=\"alternate\" href=\"https://www.pocasiaradar.cz/meteoradar\"><link hreflang=\"da-DK\" rel=\"alternate\" href=\"https://www.vejrogradar.dk/vejrradar\"><link hreflang=\"el-GR\" rel=\"alternate\" href=\"https://www.kairosradar.gr/rantar-kairou\"><link hreflang=\"en-GB\" rel=\"alternate\" href=\"https://www.weatherandradar.co.uk/weather-map\"><link hreflang=\"en-IE\" rel=\"alternate\" href=\"https://www.weatherandradar.ie/weather-map\"><link hreflang=\"en-IN\" rel=\"alternate\" href=\"https://www.weatherandradar.in/weather-map\"><link hreflang=\"en-US\" rel=\"alternate\" href=\"https://www.weatherandradar.com/weather-map\"><link hreflang=\"es-ES\" rel=\"alternate\" href=\"https://www.tiempoyradar.es/radar-meteorologico\"><link hreflang=\"es-AR\" rel=\"alternate\" href=\"https://www.tiempoyradar.com.ar/radar-meteorologico\"><link hreflang=\"es-US\" rel=\"alternate\" href=\"https://es.weatherandradar.com/radar-meteorologico\"><link hreflang=\"fr-FR\" rel=\"alternate\" href=\"https://www.meteoetradar.com/carte-meteo\"><link hreflang=\"fr-BE\" rel=\"alternate\" href=\"https://www.meteoetradar.be/carte-meteo\"><link hreflang=\"fr-CH\" rel=\"alternate\" href=\"https://www.meteoetradar.ch/carte-meteo\"><link hreflang=\"hr-HR\" rel=\"alternate\" href=\"https://www.vrijemeradar.hr/vremenski-radar\"><link hreflang=\"hu-HU\" rel=\"alternate\" href=\"https://www.idojarasesradar.hu/idojaras-terkep\"><link hreflang=\"it-IT\" rel=\"alternate\" href=\"https://www.meteoeradar.it/radar-meteo\"><link hreflang=\"lt-LT\" rel=\"alternate\" href=\"https://www.orasonline.lt/oru-zemelapis\"><link hreflang=\"lv-LV\" rel=\"alternate\" href=\"https://www.meteounradars.lv/laikapstaklu-radars\"><link hreflang=\"mk-MK\" rel=\"alternate\" href=\"https://www.vremetoiradar.com/vremenski-radar\"><link hreflang=\"nl-NL\" rel=\"alternate\" href=\"https://www.weerenradar.nl/weerradar\"><link hreflang=\"nl-BE\" rel=\"alternate\" href=\"https://www.weerenradar.be/weerradar\"><link hreflang=\"pl-PL\" rel=\"alternate\" href=\"https://www.pogodairadar.pl/radar-pogodowy\"><link hreflang=\"pt-PT\" rel=\"alternate\" href=\"https://www.tempoeradar.pt/mapa-do-tempo\"><link hreflang=\"pt-BR\" rel=\"alternate\" href=\"https://www.climaeradar.com.br/radarclima\"><link hreflang=\"ro-RO\" rel=\"alternate\" href=\"https://www.meteoradar.ro/harta-meteo\"><link hreflang=\"sk-SK\" rel=\"alternate\" href=\"https://www.pocasieradar.sk/meteoradar\"><link hreflang=\"sl-SI\" rel=\"alternate\" href=\"https://www.vremeradar.si/vremenski-radar\"><link hreflang=\"sr-Latn-RS\" rel=\"alternate\" href=\"https://www.vremeradar.rs/vremenski-radar\"><link hreflang=\"sr-Latn-ME\" rel=\"alternate\" href=\"https://www.vrijemeradar.me/vremenski-radar\"><link hreflang=\"tr-TR\" rel=\"alternate\" href=\"https://www.havadurumuveradar.com/hava-durumu-radari\"><link hreflang=\"uk-UA\" rel=\"alternate\" href=\"https://www.pogodairadar.com.ua/radar-pohody\"><style>.fullscreen-radar[_nghost-serverApp-c2904161441]   wo-back-button[_ngcontent-serverApp-c2904161441]{left:calc(env(safe-area-inset-left) + 5px);top:calc(env(safe-area-inset-top) + 5px)}iframe[_ngcontent-serverApp-c2904161441]{display:block;height:100%;border:0}.container[_ngcontent-serverApp-c2904161441]{position:relative;display:flex;flex-direction:row;height:100%;width:100%}.flex[_ngcontent-serverApp-c2904161441]{position:relative;height:100%;width:100%;display:flex;flex-direction:column}wo-back-button[_ngcontent-serverApp-c2904161441]{position:absolute;width:40px;height:40px;left:5px;top:5px}.safe-area[_ngcontent-serverApp-c2904161441]{padding-bottom:env(safe-area-inset-bottom)}.hint[_ngcontent-serverApp-c2904161441]{display:flex;background-color:#10658e;color:#fff;position:absolute;right:60px;height:40px;text-align:center;font-size:14px;line-height:18px;border-radius:8px;top:5px;width:300px;align-items:center;justify-content:center}</style><style>[_nghost-serverApp-c4010958647]{display:flex;align-items:center}img[_ngcontent-serverApp-c4010958647]{cursor:pointer}</style><link _ngcontent-serverapp-c4010958647=\"\" as=\"image\" href=\"assets/app-shell/ic_back.svg\" rel=\"preload\" fetchpriority=\"high\"><style>[_nghost-serverApp-c2903451194]{display:block;background:max(14px,env(safe-area-inset-left)) 50% no-repeat;background-size:46px 46px;cursor:pointer}.dark[_nghost-serverApp-c2903451194]{background-color:#00537f}a[_ngcontent-serverApp-c2903451194]{display:flex;align-items:center;--ripple-color: #fff;padding-left:env(safe-area-inset-left);text-indent:var(--icon-margin);height:66px;font-size:18px}a.active[_ngcontent-serverApp-c2903451194]{background-color:#ffffff1a}.icon[_ngcontent-serverApp-c2903451194]{width:32px;margin:0 14px}.badge[_ngcontent-serverApp-c2903451194]{display:inline-block;background:50%/contain no-repeat;height:30px;width:30px;margin-left:8px;vertical-align:middle}[_nghost-serverApp-c2903451194]:not(.dark)   .external[_ngcontent-serverApp-c2903451194]{outline-style:none;display:flex;justify-content:space-between}[_nghost-serverApp-c2903451194]:not(.dark)   .external[_ngcontent-serverApp-c2903451194]:after{content:\"\";background:url(assets/app-shell/ic_link_extern.svg) center no-repeat;width:35px;height:100%;opacity:.5;margin-right:8px}</style><link rel=\"stylesheet\" href=\"https://radar.wo-cloud.com/fonts/roboto/Roboto-swap-300,400,500.css\"><link rel=\"stylesheet\" href=\"https://radar.wo-cloud.com/fonts/roboto/Roboto-swap-300,400,500.css\"><link rel=\"stylesheet\" href=\"https://radar.wo-cloud.com/fonts/roboto/Roboto-swap-300,400,500.css\"><link rel=\"stylesheet\" href=\"https://radar.wo-cloud.com/fonts/roboto/WORoboto-swap-500.css\"><link rel=\"manifest\" href=\"assets/manifest/ro-RO.webmanifest\"><link rel=\"canonical\" href=\"https://www.meteoradar.ro/harta-meteo\"><style>[_nghost-serverApp-c2742001453]{--padding-top-mobile: calc(61px + env(safe-area-inset-top)) ;--padding-top-desktop: calc(21px + env(safe-area-inset-top)) ;--active-shift-y-mobile: calc(-1 * var(--padding-top-mobile) + 4px);--active-shift-y-desktop: calc(-1 * var(--padding-top-desktop) + 4px);--vertical-margin: 0px;--head-height: calc(82px + env(safe-area-inset-top)) ;--search-transform-offset: 9px;position:absolute;inset:0;z-index:var(--wo-search-z-index, 101);cursor:pointer;pointer-events:none;transition:transform .2s ease-out,opacity .2s;--search-bounds-padding-top: 5px;height:100vh}@supports (height: 100dvh){[_nghost-serverApp-c2742001453]{height:100dvh}}@media(min-height:900px)and (min-width:475px){[_nghost-serverApp-c2742001453]{--vertical-margin: 8px}}.active[_nghost-serverApp-c2742001453]{pointer-events:auto;-webkit-backdrop-filter:blur(2px);backdrop-filter:blur(2px);background:#00000012;position:fixed}.active[_nghost-serverApp-c2742001453]   .container[_ngcontent-serverApp-c2742001453]{transform:none;opacity:1}.active[_nghost-serverApp-c2742001453]:not(.always-visible)   wo-search-input[_ngcontent-serverApp-c2742001453]{pointer-events:auto;opacity:1}.active[_nghost-serverApp-c2742001453]   wo-search-input[_ngcontent-serverApp-c2742001453]{transform:translate(-260px,-50%)}.active[_nghost-serverApp-c2742001453]   wo-search-input[_ngcontent-serverApp-c2742001453], [_nghost-serverApp-c2742001453]:not(.always-visible)   wo-search-input[_ngcontent-serverApp-c2742001453]{width:355px}[_nghost-serverApp-c2742001453]:not(.always-visible)   wo-search-input[_ngcontent-serverApp-c2742001453]{opacity:0;pointer-events:none}wo-search-input[_ngcontent-serverApp-c2742001453]{position:absolute;contain:layout;z-index:1;pointer-events:auto;top:calc(env(safe-area-inset-top) / 2 + 42.5px - var(--search-bounds-padding-top) / 2);right:-200px;transform:translateY(-50%);width:283px}[_nghost-serverApp-c2742001453]:not(.transitions-active)   wo-search-input[_ngcontent-serverApp-c2742001453]{transition:transform .2s ease-out}.search-bounds[_ngcontent-serverApp-c2742001453], .container[_ngcontent-serverApp-c2742001453]{position:relative;width:100%;height:100%;display:flex;flex-direction:column}.search-bounds[_ngcontent-serverApp-c2742001453]{width:475px;margin:0 auto;align-items:center;cursor:default}.container[_ngcontent-serverApp-c2742001453]{flex-grow:1;box-shadow:0 0 6px #0003;overflow-y:auto;transition:transform .2s ease-out,opacity .2s;transform:translateY(200px);opacity:0;position:absolute}@media(min-width:522.5px){.container[_ngcontent-serverApp-c2742001453]{border-radius:14px 14px 8px 8px;margin:calc(42.5px - var(--head-height) / 2) 0;max-height:900px}}.scrollable[_ngcontent-serverApp-c2742001453]{overflow-y:auto;overflow-x:hidden;padding:12px 12px calc(12px + env(safe-area-inset-bottom));flex-grow:1;display:flex;flex-direction:column;background:#fff}.scrollable[_ngcontent-serverApp-c2742001453]    >*{flex-shrink:0}wo-search-head[_ngcontent-serverApp-c2742001453]{position:sticky;flex-shrink:0}wo-search-ad[_ngcontent-serverApp-c2742001453]{order:15}wo-clear-history[_ngcontent-serverApp-c2742001453]{order:1000}</style><style>[_nghost-serverApp-c3499072736]{position:relative;font-size:18px}[_nghost-serverApp-c3499072736]:not(.alternate)   .search-button[_ngcontent-serverApp-c3499072736]{background-color:transparent!important}input[_ngcontent-serverApp-c3499072736]{width:100%;border:none;border-radius:6px;height:48px;padding:0 40px 0 16px;outline:0;background:#fff;-webkit-appearance:none}input[_ngcontent-serverApp-c3499072736]:not(.active){box-shadow:0 3px 6px #00000029}.placeholder[_ngcontent-serverApp-c3499072736]{position:absolute;inset:0 0 0 16px;display:flex;align-items:center;pointer-events:none;color:#10658e;transition:transform .15s}.placeholder.hide[_ngcontent-serverApp-c3499072736]{opacity:0}wo-loading-spinner[_ngcontent-serverApp-c3499072736]{position:absolute;top:4px;right:0;width:40px;height:40px;cursor:pointer}.search-button[_ngcontent-serverApp-c3499072736]{position:absolute;right:-30px;top:-6px;width:60px;height:60px;background:#ffbe00 url(^assets/icons/ic_search.svg) center/90% no-repeat;transition:transform .3s,background-color .3s;border-radius:50%;cursor:pointer}.search-button.active[_ngcontent-serverApp-c3499072736]{background-color:#ffbe0000;background-image:url(^assets/icons/ic_search_b.svg);transform:translate(-28px);pointer-events:auto}</style><style>[_nghost-serverApp-c2674647421]{background:#10658e;padding:12px;padding-top:calc(12px + env(safe-area-inset-top));height:var(--head-height);display:flex;align-items:center;justify-content:space-between;border-bottom:1px solid #ffbe00}.button[_ngcontent-serverApp-c2674647421]{width:40px;height:40px;cursor:pointer;border-radius:50%}@media(hover:hover)and (pointer:fine){.button[_ngcontent-serverApp-c2674647421]:hover{background-color:#ffffff17}}.button[_ngcontent-serverApp-c2674647421]:active{background-color:#ffffff0d}.back[_ngcontent-serverApp-c2674647421]{background:url(^assets/search/ic_arrow_w.svg) center/32% no-repeat;transform:rotate(-90deg)}.edit[_ngcontent-serverApp-c2674647421]{background:url(^assets/icons/ic_edit_w.svg) center/42% no-repeat}.edit.active[_ngcontent-serverApp-c2674647421]{background-image:url(^assets/icons/ic_close.svg);background-size:40%}button[_ngcontent-serverApp-c2674647421]{border:none}</style><style>[_nghost-serverApp-c4121170390]{position:relative;background:#10658e;color:#fff;border-radius:8px;font-size:16px;overflow:hidden;padding:16px}.inner[_ngcontent-serverApp-c4121170390]{display:flex;align-items:center;justify-content:center}.delete[_ngcontent-serverApp-c4121170390]{cursor:pointer}.delete[_ngcontent-serverApp-c4121170390]:before{content:\"\";background:url(^assets/search/ic_trash_w.svg) center/contain no-repeat;display:inline-block;width:22px;height:22px;margin-right:4px;margin-top:-1px}.dialog[_ngcontent-serverApp-c4121170390]{transform:translate(50%);opacity:0;pointer-events:none;gap:16px;text-align:center;height:0}.dialog.show[_ngcontent-serverApp-c4121170390]{transform:none;opacity:1;pointer-events:auto;height:auto;margin-top:16px;transition:transform .3s ease,opacity .3s}.no[_ngcontent-serverApp-c4121170390]{border:1px solid #fff}</style><style>[_nghost-serverApp-c1361432828]{display:inline-flex;align-items:center;justify-content:center;padding:0 32px;height:32px;border-radius:4px;background-color:#10658e;color:#fff;cursor:pointer;white-space:nowrap}[_nghost-serverApp-c1361432828]:hover{background-color:#003959}.mousedown[_nghost-serverApp-c1361432828]{background-color:#00537f}.secondary[_nghost-serverApp-c1361432828]{background-color:#f2f7f9;color:#10658e}.secondary[_nghost-serverApp-c1361432828]:hover{background-color:#e6eff3;color:#003959}.block[_nghost-serverApp-c1361432828]{display:flex}.light[_nghost-serverApp-c1361432828]{background-color:#e6eff3;color:#10658e}.light[_nghost-serverApp-c1361432828]:hover{background-color:#daedf7}.lighter[_nghost-serverApp-c1361432828]{background-color:#fff;color:#10658e}.big[_nghost-serverApp-c1361432828]{height:40px;border-radius:8px;font-weight:400}.bigger[_nghost-serverApp-c1361432828]{height:48px;border-radius:8px;font-weight:400}.narrow[_nghost-serverApp-c1361432828]{padding-left:8px;padding-right:8px}.disabled[_nghost-serverApp-c1361432828]{color:#a0a0a0;background-color:#e6eff3;border:0px none;cursor:default}.call-to-action[_nghost-serverApp-c1361432828]{padding:1px 0 0 16px;border-radius:8px;box-shadow:0 2px 3px #0003;height:40px;width:fit-content;max-width:100%;font-weight:500;font-size:16px;white-space:normal;word-wrap:break-word}.call-to-action[_nghost-serverApp-c1361432828]   .arrow[_ngcontent-serverApp-c1361432828]{height:40px;width:40px;background-image:url(^assets/ic_arrow_right.svg);background-repeat:no-repeat;background-position:center;background-size:28px}</style><style>.outer[_ngcontent-serverApp-c677099593]{position:relative;margin:4px 0 12px;text-align:center}wo-fader[_ngcontent-serverApp-c677099593]     .link{color:#10658e;background-color:#f2f7f9}.edit-mode-title[_ngcontent-serverApp-c677099593]{border:none!important;order:0}.edit-mode-title.abs[_ngcontent-serverApp-c677099593]{position:absolute;inset:0}</style><style type=\"text/css\">#sp_message_iframe_1251974 { display:block; width: 100%; height: 100%; border: 0 none; } #sp_message_container_1251974 { overflow:auto;-webkit-overflow-scrolling:touch; display: none; position: fixed; z-index: 2147483647; left: 0; right: 0; bottom: 0; top: 0; height: 100%; width: 100%; max-width: 100%; max-height: 100vh;}.sp-message-open { height: 100vh !important; width: 100vw !important } .sp-message-open body { overflow: hidden !important; position: fixed !important; margin-top: 0px !important; top: 0px !important; left: 0px !important; right: 0px !important; }</style><script type=\"module\" charset=\"utf-8\" data-webpack=\"pwa:chunk-country-config.64\" src=\"country-config.64.5e79ba9dc9b036a4.js\"></script></head>\n\n  <body class=\"fullscreen\" style=\"overscroll-behavior: none; overflow: hidden;\">\n    <wo-root ng-version=\"21.0.6\" class=\"browser-rendered\" ng-server-context=\"ssr\"><wo-app-shell _nghost-serverapp-c3453211982=\"\" class=\"showing-radar\"><wo-manifest _ngcontent-serverapp-c3453211982=\"\"></wo-manifest><wo-header _ngcontent-serverapp-c3453211982=\"\" class=\"no-print large\" _nghost-serverapp-c3262266537=\"\"><div _ngcontent-serverapp-c3262266537=\"\" class=\"background\"></div><div _ngcontent-serverapp-c3262266537=\"\" class=\"header-bar\"><wo-adaptive-button-left _ngcontent-serverapp-c3262266537=\"\" _nghost-serverapp-c1466088905=\"\"><wo-fader _ngcontent-serverapp-c1466088905=\"\" class=\"visible\" style=\"opacity: 1; transition-duration: 500ms; transition-property: opacity;\"><img _ngcontent-serverapp-c1466088905=\"\" ngsrc=\"assets/app-shell/ic_menu.svg\" loading=\"eager\" alt=\"\" width=\"25\" height=\"25\" class=\"menu\" fetchpriority=\"auto\" decoding=\"auto\" ng-img=\"true\" src=\"assets/app-shell/ic_menu.svg\"><!----></wo-fader><wo-fader _ngcontent-serverapp-c1466088905=\"\" style=\"opacity: 0; pointer-events: none; transition-duration: 500ms; transition-property: opacity;\"><!----></wo-fader><!----></wo-adaptive-button-left><div _ngcontent-serverapp-c3262266537=\"\" class=\"middle-item\"><a _ngcontent-serverapp-c3262266537=\"\" class=\"logo\"><!----><div _ngcontent-serverapp-c3262266537=\"\" wologo=\"\" class=\"header-title\"><svg xmlns=\"http://www.w3.org/2000/svg\" viewBox=\"0 0 170 30\"><path d=\"M107.28 14.85V23c0 .55-.45.97-.97.97h-.45a.97.97 0 0 1-.97-.97V11.03c0-.55.45-.97.97-.97h.45c.52 0 .97.42.97.97v.32c1.13-1.04 2.36-1.94 4.34-1.94.68 0 1.23.1 1.23.1.35.06.68.32.68.78 0 .1-.06.32-.06.32l-.16.58c-.16.39-.42.68-.78.68-.2 0-.61-.06-.87-.06-1.69-.01-3.6.77-4.38 3.04zm13.3-5.44c4.24 0 5.76 2.66 5.76 5.54V23c0 .55-.45.97-.97.97h-.45a.97.97 0 0 1-.97-.97v-.65c-.78 1.29-2.03 2.11-4.01 2.11-3.1 0-5.21-1.81-5.21-4.34 0-3.37 2.82-4.56 5.95-4.56 1.75 0 2.82.3 3.27.45v-1.4c0-1.91-2.14-2.88-3.37-2.88s-2 .16-2.58.45c-.29.16-.52.26-.71.26-.23 0-.49-.1-.74-.35l-.39-.42a.776.776 0 0 1-.23-.58c0-.32.13-.55.32-.68.97-.55 2.33-1 4.33-1zm3.37 8.84c-.52-.23-1.68-.55-3.4-.55-2.3 0-3.43.9-3.43 2.43 0 1.1 1.07 1.94 2.82 1.94 1.52 0 3.24-.94 4.01-2.85v-.97zm18.15 5.72h-.45a.97.97 0 0 1-.97-.97v-.65c-.78.94-2.36 2.11-4.34 2.11-4.24 0-7.16-3.24-7.16-7.48 0-4.17 2.91-7.44 7.16-7.44 1.75 0 3.4.9 4.34 2.11V1.97c0-.55.45-.97.97-.97h.45c.52 0 .97.42.97.97V23c0 .55-.45.97-.97.97zm-5.75-12.03c-2.88 0-4.79 2.17-4.79 5.04 0 2.88 1.91 5.15 4.79 5.15 1.52 0 4.66-1.01 4.66-5.15 0-3.88-3.15-5.04-4.66-5.04zm15.69-2.53c4.24 0 5.76 2.66 5.76 5.54V23c0 .55-.45.97-.97.97h-.45a.97.97 0 0 1-.97-.97v-.65c-.78 1.29-2.03 2.11-4.01 2.11-3.1 0-5.21-1.81-5.21-4.34 0-3.37 2.82-4.56 5.95-4.56 1.75 0 2.82.3 3.27.45v-1.4c0-1.91-2.14-2.88-3.37-2.88s-2 .16-2.58.45c-.29.16-.52.26-.71.26-.23 0-.49-.1-.74-.35l-.39-.42a.776.776 0 0 1-.23-.58c0-.32.13-.55.32-.68.96-.55 2.32-1 4.33-1zm3.37 8.84c-.52-.23-1.68-.55-3.4-.55-2.3 0-3.43.9-3.43 2.43 0 1.1 1.07 1.94 2.82 1.94 1.52 0 3.24-.94 4.01-2.85v-.97zm8.34-3.4V23c0 .55-.45.97-.97.97h-.45a.97.97 0 0 1-.97-.97V11.03c0-.55.45-.97.97-.97h.45c.52 0 .97.42.97.97v.32c1.13-1.04 2.36-1.94 4.34-1.94.68 0 1.23.1 1.23.1.35.06.68.32.68.78 0 .1-.06.32-.06.32l-.16.58c-.16.39-.42.68-.78.68-.2 0-.61-.06-.87-.06-1.69-.01-3.6.77-4.38 3.04z\" fill=\"#fff\"></path><path d=\"M100.87 15.38l-.04-.37a.773.773 0 0 0-.28-.53.74.74 0 0 0-.57-.16c-.17.03-.61.02-.65.02-.76 0-1.77-.15-2.79-.76-.08-.06-1.42-1.16-1.42-1.16l-1.08 1.66.04.06c1.16 1.8.9 3.33.89 3.37 0 3.7-3.54 5.24-5.45 5.24-3.05 0-5.52-2.47-5.52-5.52 0-2 1.22-4.01 2.9-4.78.14-.06.67-.28 1.06-.44.45-.18 1.1-.45 1.43-.57 1.56-.55 3.42-1.66 3.42-3.78 0-2.31-1.72-4.12-3.93-4.12a4.12 4.12 0 0 0-4.12 4.12c0 1.24.52 2.35 1.5 3.19l-.69.52c-1.28.88-3.41 2.81-3.41 5.85 0 4.06 3.3 7.36 7.36 7.36 1.51 0 3.18-.59 4.48-1.58 1.19-.91 2.65-2.61 2.87-5.57 0-.01.09-.62-.08-1.54l-.01-.02c1.24.48 2.47.51 3.41.33.24-.05.4-.12.53-.28.12-.14.18-.34.15-.54zM88.85 5.24c1.29 0 2.31 1.09 2.31 2.47 0 .79-.76 1.95-2.9 2.63l-.18.06-.14-.12c-1.05-.93-1.56-1.43-1.56-2.56 0-1.53 1.28-2.48 2.47-2.48z\" fill=\"#fbbc12\"></path><path d=\"M92.51 19.71c-.65.03-1.32-.01-2.01-.14.4-.67.64-1.42.7-2.19.59.1 1.21.14 1.86.12-.07.87-.27 1.59-.55 2.21m.97-2.23c.52-.04 1.05-.13 1.6-.25l-.04-.43c-.49.15-1.01.28-1.56.34-.03-.86-.24-1.78-.62-2.72.2 1.05.26 1.95.22 2.75-.61.04-1.23.01-1.87-.1.04-.93-.14-1.94-.52-2.98.17 1.11.2 2.07.12 2.9-.96-.21-1.94-.58-2.91-1.18.78.73 1.76 1.22 2.87 1.48-.12.87-.36 1.59-.67 2.19-.96-.24-1.87-.62-2.71-1.13.7.66 1.58 1.13 2.55 1.4-.48.82-1.08 1.4-1.64 1.84.88-.47 1.56-1.07 2.03-1.76.64.14 1.31.21 2.01.2-.45.87-1.05 1.49-1.61 1.96.92-.53 1.6-1.2 2.05-1.97.6-.04 1.22-.14 1.84-.27l.18-.49c-.58.21-1.2.35-1.85.42.34-.68.51-1.42.53-2.2\" fill=\"#fbbc12\"></path><path d=\"M17.05 24.28h-.45c-.53 0-.98-.42-.98-.98v-5.93c0-2.26-.13-5.31-1.87-5.31-1.37 0-3.05 1.44-3.53 3.05v8.19c0 .55-.45.98-.98.98h-.46c-.53 0-.98-.42-.98-.98v-5.93c0-2.26 0-5.31-1.87-5.31-1.54 0-2.91 1.44-3.5 3.08v8.15c0 .55-.45.98-.98.98H.98A.966.966 0 0 1 0 23.3V11.18c0-.55.45-.98.98-.98h.45c.52 0 .98.42.98.98v.59c.57-.85 2.14-2.07 3.7-2.07 1.71 0 2.46.62 3.44 2.07 1.34-1.44 2.62-2.07 4.19-2.07 3.11 0 4.28 2.78 4.28 7v6.58c.01.57-.44 1-.97 1zm15.29-3.77c.2-.2.42-.3.69-.3a1 1 0 0 1 .69.3l.33.33c.2.2.3.42.3.69s-.1.46-.3.69c-1.14 1.34-3.24 2.72-6.02 2.72-4.25 0-7.04-3.44-7.04-7.69s2.78-7.69 7.04-7.69 7.04 3.44 7.04 7.79c0 .56-.45.98-.98.98H23.5s.65 4.19 4.52 4.19c1.89-.01 3.37-.93 4.32-2.01zm.19-4.29c-.52-2.35-1.83-4.32-4.52-4.32-2.69 0-4 1.96-4.52 4.32h9.04zm5.86 2.56v-6.32h-1.28c-.56 0-.98-.45-.98-.98v-.3c0-.52.42-.98.98-.98h1.28V6.34c0-.56.45-.98.98-.98h.45c.53 0 .98.42.98.98v3.86h3.08c.56 0 .98.45.98.98v.3c0 .52-.42.98-.98.98H40.8v6.61c0 1.77 1.47 2.68 3.08 3.11.59.16.98.45.98.98v.45c0 .53-.42.92-.98.92-.84.01-5.49-.65-5.49-5.75zm19.71 1.73c.2-.2.42-.3.69-.3a1 1 0 0 1 .69.3l.33.33c.2.2.3.42.3.69s-.1.46-.3.69c-1.14 1.34-3.24 2.72-6.02 2.72-4.25 0-7.04-3.44-7.04-7.69s2.78-7.69 7.04-7.69 7.04 3.44 7.04 7.79c0 .56-.45.98-.98.98H49.26s.65 4.19 4.52 4.19c1.89-.01 3.37-.93 4.32-2.01zm.19-4.29c-.53-2.35-1.83-4.32-4.52-4.32-2.69 0-4 1.96-4.52 4.32h9.04zm12.96-6.68c4.25 0 7.69 3.44 7.69 7.69s-3.44 7.69-7.69 7.69-7.69-3.44-7.69-7.69 3.43-7.69 7.69-7.69zm0 12.97c2.91 0 5.31-2.39 5.31-5.31s-2.39-5.31-5.31-5.31c-2.91 0-5.31 2.39-5.31 5.31s2.4 5.31 5.31 5.31z\" fill=\"#fff\"></path></svg></div><!----></a></div><!----><wo-progress _ngcontent-serverapp-c3262266537=\"\" _nghost-serverapp-c4007100336=\"\" style=\"opacity: 0; display: none;\"><div _ngcontent-serverapp-c4007100336=\"\" class=\"progress-line\"></div></wo-progress><wo-menu _ngcontent-serverapp-c3262266537=\"\" data-testid=\"menu\" _nghost-serverapp-c4137958609=\"\" class=\"first-render\"><div _ngcontent-serverapp-c4137958609=\"\" class=\"backdrop\"></div><div _ngcontent-serverapp-c4137958609=\"\" class=\"menu\"><div _ngcontent-serverapp-c4137958609=\"\" class=\"scroll-blocking-svc-scrollable-item\"><!----><wo-menu-item _ngcontent-serverapp-c4137958609=\"\" icon=\"home\" _nghost-serverapp-c2903451194=\"\" style=\"background-image: url(&quot;assets/app-shell/ic_home.svg&quot;);\"><div _ngcontent-serverapp-c2903451194=\"\" woripple=\"\"><!----><a _ngcontent-serverapp-c2903451194=\"\" routerlinkactive=\"active\" href=\"/\"><span _ngcontent-serverapp-c4137958609=\"\">Acasă</span><!----></a><!----><!----></div></wo-menu-item><wo-menu-item _ngcontent-serverapp-c4137958609=\"\" icon=\"weather\" _nghost-serverapp-c2903451194=\"\" style=\"background-image: url(&quot;assets/app-shell/ic_weather.svg&quot;);\"><div _ngcontent-serverapp-c2903451194=\"\" woripple=\"\"><!----><a _ngcontent-serverapp-c2903451194=\"\" routerlinkactive=\"active\" href=\"/vremea/bucuresti/6220131\"><span _ngcontent-serverapp-c4137958609=\"\" class=\"placemark\"> Vremea București </span><!----></a><!----><!----></div></wo-menu-item><!----><wo-menu-item _ngcontent-serverapp-c4137958609=\"\" icon=\"weatherradar\" _nghost-serverapp-c2903451194=\"\" style=\"background-image: url(&quot;assets/app-shell/ic_weatherradar.svg&quot;);\"><div _ngcontent-serverapp-c2903451194=\"\" woripple=\"\"><!----><a _ngcontent-serverapp-c2903451194=\"\" routerlinkactive=\"active\" href=\"/harta-meteo/bucuresti/6220131?layer=wr&amp;center=44.4323,26.1063&amp;placemark=44.4323,26.1063\"><span _ngcontent-serverapp-c4137958609=\"\">Radar meteo</span><!----></a><!----><!----></div></wo-menu-item><wo-menu-item _ngcontent-serverapp-c4137958609=\"\" icon=\"rainradar\" _nghost-serverapp-c2903451194=\"\" style=\"background-image: url(&quot;assets/app-shell/ic_rainradar.svg&quot;);\"><div _ngcontent-serverapp-c2903451194=\"\" woripple=\"\"><!----><a _ngcontent-serverapp-c2903451194=\"\" routerlinkactive=\"active\" href=\"/harta-meteo/bucuresti/6220131?layer=rr&amp;center=44.4323,26.1063&amp;placemark=44.4323,26.1063\"><span _ngcontent-serverapp-c4137958609=\"\">Radar ploaie</span><!----></a><!----><!----></div></wo-menu-item><wo-menu-item _ngcontent-serverapp-c4137958609=\"\" icon=\"temperaturmap\" _nghost-serverapp-c2903451194=\"\" style=\"background-image: url(&quot;assets/app-shell/ic_temperaturmap.svg&quot;);\"><div _ngcontent-serverapp-c2903451194=\"\" woripple=\"\"><!----><a _ngcontent-serverapp-c2903451194=\"\" routerlinkactive=\"active\" href=\"/harta-meteo/bucuresti/6220131?layer=tr&amp;center=44.4323,26.1063&amp;placemark=44.4323,26.1063\"><span _ngcontent-serverapp-c4137958609=\"\">Radar temperaturi</span><!----></a><!----><!----></div></wo-menu-item><wo-menu-item _ngcontent-serverapp-c4137958609=\"\" icon=\"wind\" _nghost-serverapp-c2903451194=\"\" style=\"background-image: url(&quot;assets/app-shell/ic_wind.svg&quot;);\"><div _ngcontent-serverapp-c2903451194=\"\" woripple=\"\"><!----><a _ngcontent-serverapp-c2903451194=\"\" routerlinkactive=\"active\" href=\"/harta-meteo/bucuresti/6220131?layer=gr&amp;center=44.4323,26.1063&amp;placemark=44.4323,26.1063\"><span _ngcontent-serverapp-c4137958609=\"\">Radar vânt</span><!----></a><!----><!----></div></wo-menu-item><wo-menu-item _ngcontent-serverapp-c4137958609=\"\" icon=\"lightning\" _nghost-serverapp-c2903451194=\"\" style=\"background-image: url(&quot;assets/app-shell/ic_lightning.svg&quot;);\"><div _ngcontent-serverapp-c2903451194=\"\" woripple=\"\"><!----><a _ngcontent-serverapp-c2903451194=\"\" routerlinkactive=\"active\" href=\"/harta-meteo/bucuresti/6220131?layer=lr&amp;center=44.4323,26.1063&amp;placemark=44.4323,26.1063\"><span _ngcontent-serverapp-c4137958609=\"\">Radar fulgere</span><!----></a><!----><!----></div></wo-menu-item><wo-menu-item _ngcontent-serverapp-c4137958609=\"\" icon=\"weatherticker\" _nghost-serverapp-c2903451194=\"\" style=\"background-image: url(&quot;assets/app-shell/ic_weatherticker.svg&quot;);\"><div _ngcontent-serverapp-c2903451194=\"\" woripple=\"\"><!----><a _ngcontent-serverapp-c2903451194=\"\" routerlinkactive=\"active\" href=\"/stiri-meteo/cele-mai-recente\"><span _ngcontent-serverapp-c4137958609=\"\">Știri meteo</span><!----></a><!----><!----></div></wo-menu-item><wo-menu-item _ngcontent-serverapp-c4137958609=\"\" icon=\"teaser\" _nghost-serverapp-c2903451194=\"\" style=\"background-image: url(&quot;assets/app-shell/ic_teaser.svg&quot;);\"><div _ngcontent-serverapp-c2903451194=\"\" woripple=\"\"><!----><a _ngcontent-serverapp-c2903451194=\"\" routerlinkactive=\"active\" href=\"/stiri-meteo/articole-recomandate\"><span _ngcontent-serverapp-c4137958609=\"\">Articole recomandate</span><!----></a><!----><!----></div></wo-menu-item><!----><!----><!----><wo-menu-item _ngcontent-serverapp-c4137958609=\"\" icon=\"product_marketing\" _nghost-serverapp-c2903451194=\"\" style=\"background-image: url(&quot;assets/app-shell/ic_product_marketing.svg&quot;);\"><div _ngcontent-serverapp-c2903451194=\"\" woripple=\"\"><!----><a _ngcontent-serverapp-c2903451194=\"\" routerlinkactive=\"active\" href=\"/descopera-aplicatia\"><span _ngcontent-serverapp-c4137958609=\"\">Descoperă aplicația</span><!----></a><!----><!----></div></wo-menu-item><!----><wo-menu-item _ngcontent-serverapp-c4137958609=\"\" icon=\"widgets\" _nghost-serverapp-c2903451194=\"\" style=\"background-image: url(&quot;assets/app-shell/ic_widgets.svg&quot;);\"><div _ngcontent-serverapp-c2903451194=\"\" woripple=\"\"><!----><a _ngcontent-serverapp-c2903451194=\"\" routerlinkactive=\"active\" href=\"/widget-meteo\"><span _ngcontent-serverapp-c4137958609=\"\">Widget meteo</span><!----></a><!----><!----></div></wo-menu-item><wo-menu-item _ngcontent-serverapp-c4137958609=\"\" icon=\"contact\" _nghost-serverapp-c2903451194=\"\" style=\"background-image: url(&quot;assets/app-shell/ic_contact.svg&quot;);\"><div _ngcontent-serverapp-c2903451194=\"\" woripple=\"\"><!----><a _ngcontent-serverapp-c2903451194=\"\" routerlinkactive=\"active\" href=\"/informatii-legale\"><span _ngcontent-serverapp-c4137958609=\"\">Contact</span><!----></a><!----><!----></div></wo-menu-item><wo-menu-item _ngcontent-serverapp-c4137958609=\"\" icon=\"apps\" _nghost-serverapp-c2903451194=\"\" style=\"background-image: url(&quot;assets/app-shell/ic_apps.svg&quot;);\"><div _ngcontent-serverapp-c2903451194=\"\" woripple=\"\"><a _ngcontent-serverapp-c2903451194=\"\" class=\"external\" target=\"_blank\" href=\"https://aplicatie.meteoradar.ro/pHdP/roROapplinkPWA\"><span _ngcontent-serverapp-c2903451194=\"\"><span _ngcontent-serverapp-c4137958609=\"\">Aplicații</span><!----><!----></span></a><!----><!----><!----></div></wo-menu-item><!----></div></div><!----></wo-menu><wo-search _ngcontent-serverapp-c3262266537=\"\" _nghost-serverapp-c2742001453=\"\" class=\"always-visible transitions-active\"><div _ngcontent-serverapp-c2742001453=\"\" class=\"search-bounds\"><wo-search-input _ngcontent-serverapp-c2742001453=\"\" _nghost-serverapp-c3499072736=\"\" class=\"alternate\"><form _ngcontent-serverapp-c3499072736=\"\"><!----><div _ngcontent-serverapp-c3499072736=\"\" class=\"search-button\"></div><!----><input _ngcontent-serverapp-c3499072736=\"\" id=\"wo-search-input\" autocomplete=\"off\"><label _ngcontent-serverapp-c3499072736=\"\" for=\"wo-search-input\" class=\"placeholder shifted\"> Vremea în ... </label></form></wo-search-input><div _ngcontent-serverapp-c2742001453=\"\" class=\"container\" aria-hidden=\"false\"><wo-search-head _ngcontent-serverapp-c2742001453=\"\" _nghost-serverapp-c2674647421=\"\"><button _ngcontent-serverapp-c2674647421=\"\" class=\"button back\" aria-label=\"Închide\"></button><!----></wo-search-head><div _ngcontent-serverapp-c2742001453=\"\" class=\"scrollable scroll-blocking-svc-scrollable-item\"><wo-edit-mode-title _ngcontent-serverapp-c2742001453=\"\" _nghost-serverapp-c677099593=\"\"><!----></wo-edit-mode-title><!----><!----><!----><wo-clear-history _ngcontent-serverapp-c2742001453=\"\" _nghost-serverapp-c4121170390=\"\" style=\"display: none;\"><div _ngcontent-serverapp-c4121170390=\"\" class=\"inner delete\"> Șterge istoricul\n</div><div _ngcontent-serverapp-c4121170390=\"\" class=\"inner dialog\"><wo-button _ngcontent-serverapp-c4121170390=\"\" class=\"lighter\" _nghost-serverapp-c1361432828=\"\">Da<div _ngcontent-serverapp-c1361432828=\"\" class=\"arrow\"></div></wo-button><wo-button _ngcontent-serverapp-c4121170390=\"\" class=\"no\" _nghost-serverapp-c1361432828=\"\">Nu<div _ngcontent-serverapp-c1361432828=\"\" class=\"arrow\"></div></wo-button></div></wo-clear-history></div></div></div></wo-search><!----></div></wo-header><div _ngcontent-serverapp-c3453211982=\"\" class=\"app-content fullscreen-content\" style=\"background-color: rgb(255, 255, 255);\"><div _ngcontent-serverapp-c3453211982=\"\" class=\"container\"><router-outlet _ngcontent-serverapp-c3453211982=\"\"></router-outlet><wo-weather-radar _nghost-serverapp-c3402772825=\"\"><wo-radar _ngcontent-serverapp-c3402772825=\"\" _nghost-serverapp-c2904161441=\"\"><div _ngcontent-serverapp-c2904161441=\"\" class=\"container\"><!----><div _ngcontent-serverapp-c2904161441=\"\" class=\"flex\"><iframe _ngcontent-serverapp-c2904161441=\"\" id=\"radarIframe\" allow=\"web-share\" src=\"https://radar.wo-cloud.com/pwa/?bounds=49,20,41,30&amp;tz=UTC&amp;tf=HH:mm&amp;windunit=kmh&amp;lang=ro-RO&amp;safeAreaTop=true&amp;safeAreaBottom=true&amp;desktop=true&amp;fadeTop=false\" title=\"Radar meteo\"></iframe><!----><wo-back-button _ngcontent-serverapp-c2904161441=\"\" _nghost-serverapp-c4010958647=\"\"><img _ngcontent-serverapp-c4010958647=\"\" ngsrc=\"assets/app-shell/ic_back.svg\" alt=\"\" width=\"40\" height=\"40\" priority=\"\" loading=\"eager\" fetchpriority=\"high\" decoding=\"sync\" ng-img=\"true\" src=\"assets/app-shell/ic_back.svg\"></wo-back-button><!----></div><!----></div></wo-radar><!----></wo-weather-radar><!----></div><wo-skyscraper-ads _ngcontent-serverapp-c3453211982=\"\" _nghost-serverapp-c839895721=\"\" class=\"large-header\"><!----></wo-skyscraper-ads><!----></div><!----><!----></wo-app-shell><wo-injection-anchor></wo-injection-anchor><!----></wo-root>\n    <noscript> JavaScript is required to view this page. </noscript>\n  <script src=\"runtime.e1bacfee529af53b.js\" type=\"module\"></script><script src=\"polyfills.80281b1eb0ea87dc.js\" type=\"module\"></script><script src=\"main.5323c288efa51451.js\" type=\"module\"></script>\n\n<script id=\"serverApp-state\" type=\"application/json\">{\"https://api.wo-cloud.com/my-geo-config?language=ro&region=RO\":{\"country\":\"DE\",\"subdivision\":\"HE\",\"tickerRegion\":\"RO\",\"searchRegion\":\"RO\"},\"https://tiles.wo-cloud.com/country-radar-bounds/RO?\":{\"bounds\":{\"north\":49,\"south\":41,\"east\":30,\"west\":20},\"aspectRatio\":1.22},\"https://api-app.wetteronline.de/search/topcities?av=2&c=cHdhOnNCcDlyQnprcHhrOTMrPWA=&language=ro&region=RO&application=pwa&mv=8\":[{\"geoObject\":{\"displayName\":{\"primaryName\":\"București\",\"secondaryNames\":[\"București\",\"România\"]},\"normalizedName\":\"bucuresti\",\"locationName\":\"București\",\"sublocationName\":null,\"zipCode\":null,\"districtName\":null,\"substateName\":\"București\",\"stateName\":\"România\",\"iso-3166-1\":\"RO\",\"iso-3166-2\":\"RO-B\",\"latitude\":44.4323,\"longitude\":26.1063,\"altitude\":83,\"timeZone\":\"Europe/Bucharest\",\"geoObjectKey\":\"6220131\",\"topographicLabels\":[]},\"pwa\":{\"urlPath\":\"bucuresti\",\"urlPaths\":{\"bg-BG\":\"bukures\",\"bs-BA\":\"bukurest\",\"cs-CZ\":\"bukurest\",\"da-DK\":\"bukarest\",\"el-GR\":\"boukouresti\",\"en-GB\":\"bucharest\",\"en-IE\":\"bucharest\",\"en-IN\":\"bucharest\",\"en-US\":\"bucharest\",\"es-AR\":\"bucarest\",\"es-ES\":\"bucarest\",\"es-US\":\"bucarest\",\"fr-BE\":\"bucarest\",\"fr-CH\":\"bucarest\",\"fr-FR\":\"bucarest\",\"hr-HR\":\"bukurest\",\"hu-HU\":\"bukarest\",\"it-IT\":\"bucarest\",\"lt-LT\":\"bukarestas\",\"lv-LV\":\"bukareste\",\"mk-MK\":\"bukurest\",\"nl-BE\":\"boekarest\",\"nl-NL\":\"boekarest\",\"pl-PL\":\"bukareszt\",\"pt-BR\":\"bucareste\",\"pt-PT\":\"bucareste\",\"ru-UA\":\"buharest\",\"sk-SK\":\"bukurest\",\"sl-SI\":\"bukaresta\",\"tr-TR\":\"buekres\",\"uk-UA\":\"buharest\"}},\"contentKeys\":{\"forecastKey\":{\"location_id\":\"15420\"},\"aqiKey\":{\"location_id\":\"15420\"},\"pollenKey\":{\"location_id\":\"15420\"},\"nowcastKey\":{\"woGridKey\":{\"gridLatitude\":\"44.46\",\"gridLongitude\":\"26.08\"}},\"astroKey\":{\"woGridKey\":{\"gridLatitude\":\"44.46\",\"gridLongitude\":\"26.08\"}},\"skiKey\":{\"latitude\":\"44.4323\",\"longitude\":\"26.1063\"},\"waterKey\":null}},{\"geoObject\":{\"displayName\":{\"primaryName\":\"Cluj-Napoca\",\"secondaryNames\":[\"Cluj\",\"România\"]},\"normalizedName\":\"cluj-napoca\",\"locationName\":\"Cluj-Napoca\",\"sublocationName\":null,\"zipCode\":null,\"districtName\":null,\"substateName\":\"Cluj\",\"stateName\":\"România\",\"iso-3166-1\":\"RO\",\"iso-3166-2\":\"RO-CJ\",\"latitude\":46.7667,\"longitude\":23.6,\"altitude\":352,\"timeZone\":\"Europe/Bucharest\",\"geoObjectKey\":\"10599686\",\"topographicLabels\":[]},\"pwa\":{\"urlPath\":\"cluj-napoca\",\"urlPaths\":{\"bg-BG\":\"kluz-napoka\",\"cs-CZ\":\"kluz\",\"el-GR\":\"klouz-napoka\",\"hu-HU\":\"kolozsvar\",\"lt-LT\":\"kluzas-napoka\",\"lv-LV\":\"kluza-napoka\",\"pl-PL\":\"kluz-napoka\",\"ru-UA\":\"kluz-napoka\",\"sk-SK\":\"kluz\",\"tr-TR\":\"kalosvar\",\"uk-UA\":\"kluz-napoka\"}},\"contentKeys\":{\"forecastKey\":{\"location_id\":\"15120\"},\"aqiKey\":{\"location_id\":\"15120\"},\"pollenKey\":{\"location_id\":\"15120\"},\"nowcastKey\":{\"woGridKey\":{\"gridLatitude\":\"46.80\",\"gridLongitude\":\"23.60\"}},\"astroKey\":{\"woGridKey\":{\"gridLatitude\":\"46.74\",\"gridLongitude\":\"23.60\"}},\"skiKey\":{\"latitude\":\"46.7667\",\"longitude\":\"23.6000\"},\"waterKey\":null}},{\"geoObject\":{\"displayName\":{\"primaryName\":\"Timișoara\",\"secondaryNames\":[\"Timiș\",\"România\"]},\"normalizedName\":\"timisoara\",\"locationName\":\"Timișoara\",\"sublocationName\":null,\"zipCode\":null,\"districtName\":null,\"substateName\":\"Timiș\",\"stateName\":\"România\",\"iso-3166-1\":\"RO\",\"iso-3166-2\":\"RO-TM\",\"latitude\":45.7537,\"longitude\":21.2257,\"altitude\":96,\"timeZone\":\"Europe/Bucharest\",\"geoObjectKey\":\"2859256\",\"topographicLabels\":[]},\"pwa\":{\"urlPath\":\"timisoara\",\"urlPaths\":{\"cs-CZ\":\"temesvar\",\"hr-HR\":\"temisvar\",\"hu-HU\":\"temesvar\",\"tr-TR\":\"temesvar\"}},\"contentKeys\":{\"forecastKey\":{\"location_id\":\"15247\"},\"aqiKey\":{\"location_id\":\"15247\"},\"pollenKey\":{\"location_id\":\"15247\"},\"nowcastKey\":{\"woGridKey\":{\"gridLatitude\":\"45.72\",\"gridLongitude\":\"21.20\"}},\"astroKey\":{\"woGridKey\":{\"gridLatitude\":\"45.78\",\"gridLongitude\":\"21.20\"}},\"skiKey\":{\"latitude\":\"45.7537\",\"longitude\":\"21.2257\"},\"waterKey\":null}},{\"geoObject\":{\"displayName\":{\"primaryName\":\"Iași\",\"secondaryNames\":[\"Iași\",\"România\"]},\"normalizedName\":\"iasi\",\"locationName\":\"Iași\",\"sublocationName\":null,\"zipCode\":null,\"districtName\":null,\"substateName\":\"Iași\",\"stateName\":\"România\",\"iso-3166-1\":\"RO\",\"iso-3166-2\":\"RO-IS\",\"latitude\":47.1667,\"longitude\":27.6,\"altitude\":66,\"timeZone\":\"Europe/Bucharest\",\"geoObjectKey\":\"16822260\",\"topographicLabels\":[]},\"pwa\":{\"urlPath\":\"iasi\",\"urlPaths\":{\"bg-BG\":\"as\",\"cs-CZ\":\"jasy\",\"el-GR\":\"iasio\",\"hu-HU\":\"jaszvasar\",\"lt-LT\":\"jasai\",\"lv-LV\":\"jasi\",\"pl-PL\":\"jassy\",\"ru-UA\":\"assy\",\"sk-SK\":\"jasy\",\"tr-TR\":\"yas\",\"uk-UA\":\"assi\"}},\"contentKeys\":{\"forecastKey\":{\"location_id\":\"15090\"},\"aqiKey\":{\"location_id\":\"15090\"},\"pollenKey\":{\"location_id\":\"15090\"},\"nowcastKey\":{\"woGridKey\":{\"gridLatitude\":\"47.16\",\"gridLongitude\":\"27.60\"}},\"astroKey\":{\"woGridKey\":{\"gridLatitude\":\"47.16\",\"gridLongitude\":\"27.60\"}},\"skiKey\":{\"latitude\":\"47.1667\",\"longitude\":\"27.6000\"},\"waterKey\":null}}]}</script><iframe name=\"__tcfapiLocator\" style=\"display: none;\"></iframe><div id=\"sp_message_container_1251974\" aria-modal=\"true\" aria-labelledby=\"sp_message_iframe_1251974\" role=\"dialog\" style=\"display: block;\"><iframe src=\"https://cmp.wetteronline.de/index.html?message_id=1251974&amp;consentUUID=undefined&amp;preload_message=true&amp;hasCsp=true&amp;version=v1&amp;consent_origin=https%3A%2F%2Fcmp.wetteronline.de%2Fconsent%2Ftcfv2&amp;mms_origin=https%3A%2F%2Fcmp.wetteronline.de%2Fmms%2Fv2\" id=\"sp_message_iframe_1251974\" title=\"SP Consent Message\"></iframe></div></body></html>",
    "metadata": {
      "apple-mobile-web-app-status-bar-style": "black-translucent",
      "description": "Radar meteo - vezi evoluția vremii interactiv și în timp real: ploi, furtuni, ninsori și nori, în România cât și în întreaga lume.",
      "lang": "ro",
      "og:description": "Radar meteo - vezi evoluția vremii interactiv și în timp real: ploi, furtuni, ninsori și nori, în România cât și în întreaga lume.",
      "og:image": "https://www.meteoradar.ro/assets/logos/preview-teaser/ro-RO_logo-isobars_16x9.png",
      "og:locale": "ro_RO",
      "og:url": "https://www.meteoradar.ro/harta-meteo",
      "robots": "index,follow",
      "theme-color": "#10658e",
      "viewport": "viewport-fit=contain"
    },
    "title": "Ploaie, furtuni, ninsori și nori în timp real",
    "url": "https://www.meteoradar.ro/harta-meteo",
    "usage": {
      "tokens": 17997
    }
  },
  "meta": {
    "usage": {
      "tokens": 17997
    }
  },
  "status": 20000
}
